gino_starlette.py
gino_starlette-0.1.4.dist-info/entry_points.txt
gino_starlette-0.1.4.dist-info/LICENSE
gino_starlette-0.1.4.dist-info/WHEEL
gino_starlette-0.1.4.dist-info/METADATA
gino_starlette-0.1.4.dist-info/RECORD
