Metadata-Version: 2.1
Name: gino-starlette
Version: 0.1.4
Summary: An extension for GINO to integrate with Starlette
Home-page: https://github.com/python-gino/gino-starlette
License: BSD-3-Clause
Keywords: sqlalchemy,python3,starlette,gino
Author: Tony Wang
Author-email: wwwjfy@gmail.com
Maintainer: Aobo Shi
Maintainer-email: shiaobo8@gmail.com
Requires-Python: >=3.6.2,<4.0.0
Classifier: Development Status :: 4 - Beta
Classifier: Intended Audience :: Developers
Classifier: License :: OSI Approved :: BSD License
Classifier: Natural Language :: English
Classifier: Programming Language :: Python :: 3
Classifier: Programming Language :: Python :: 3.10
Classifier: Programming Language :: Python :: 3.6
Classifier: Programming Language :: Python :: 3.7
Classifier: Programming Language :: Python :: 3.8
Classifier: Programming Language :: Python :: 3.9
Requires-Dist: gino (>=1.0.1,<2.0.0)
Requires-Dist: starlette (>=0.17,<0.18)
Project-URL: Documentation, https://python-gino.org/docs/
Project-URL: Repository, https://github.com/python-gino/gino-starlette
